ossify/__init__.py
ossify/algorithms.py
ossify/base.py
ossify/data_layers.py
ossify/file_io.py
ossify/graph_functions.py
ossify/plot.py
ossify/sync_classes.py
ossify/translate.py
ossify/utils.py
ossify-0.0.4.dist-info/METADATA
ossify-0.0.4.dist-info/WHEEL
ossify-0.0.4.dist-info/licenses/LICENSE
ossify-0.0.4.dist-info/RECORD
