Metadata-Version: 2.4
Name: ossify
Version: 0.0.4
Summary: Mesh and skeleton analysis
Author-email: Casey Schneider-Mizell <caseysm@gmail.com>
License-File: LICENSE
Classifier: License :: OSI Approved :: MIT License
Requires-Python: >=3.11
Requires-Dist: caveclient>=7.6.0
Requires-Dist: cloud-files>=5.8.0
Requires-Dist: matplotlib>=3.10.6
Requires-Dist: morphsync==0.1.0
Requires-Dist: numpy>=2.0.2
Requires-Dist: orjson>=3.10.15
Requires-Dist: scipy>=1.15
Requires-Dist: trimesh>=4.6.2
Provides-Extra: legacy
Requires-Dist: h5py>=3.14.0; extra == 'legacy'
